<?xml version="1.0" encoding="UTF-8"?><epp xmlns="urn:ietf:params:xml:ns:epp-1.0"><command><login><clID><![CDATA[OTE1207-LH1]]></clID><pw><![CDATA[RzHF77YVkCN%4Hfh]]></pw><options><version><![CDATA[1.0]]></version><lang><![CDATA[en-US]]></lang></options><svcs><objURI><![CDATA[urn:ietf:params:xml:ns:contact-1.0]]></objURI><objURI><![CDATA[urn:ietf:params:xml:ns:domain-1.0]]></objURI><objURI><![CDATA[urn:ietf:params:xml:ns:host-1.0]]></objURI><svcExtension><extURI><![CDATA[urn:ietf:params:xml:ns:rgp-1.0]]></extURI></svcExtension></svcs></login><clTRID><![CDATA[7f38e898-ec77-4583-9009-de8f6c5284f6]]></clTRID></command></epp>